sense.py
scientisst/__init__.py
scientisst/constants.py
scientisst/exceptions.py
scientisst/frame.py
scientisst/scientisst.py
scientisst/state.py
scientisst/esp_adc/__init__.py
scientisst/esp_adc/constants.py
scientisst/esp_adc/esp_adc.py
scientisst/esp_adc/lut_adc.py
sense_src/__init__.py
sense_src/arg_parser.py
sense_src/custom_script.py
sense_src/device_picker.py
sense_src/file_writer.py
sense_src/stream_lsl.py
sense_src/thread_builder.py
scientisst_sense-1.2.0.dist-info/LICENSE
scientisst_sense-1.2.0.dist-info/METADATA
scientisst_sense-1.2.0.dist-info/WHEEL
scientisst_sense-1.2.0.dist-info/entry_points.txt
scientisst_sense-1.2.0.dist-info/top_level.txt
scientisst_sense-1.2.0.dist-info/RECORD
