Metadata-Version: 2.1
Name: scientisst-sense
Version: 1.2.0
Summary: The ScientISST SENSE Python API
Home-page: https://github.com/scientisst/scientisst-sense-api-python
Author: ScientISST
Author-email: developer@scientisst.com
Project-URL: Bug Tracker, https://github.com/scientisst/scientisst-sense-api-python/issues
Project-URL: Documentation, https://scientisst.github.io/scientisst-sense-api-python
Classifier: Programming Language :: Python :: 3
Classifier: License :: OSI Approved :: MIT License
Classifier: Operating System :: OS Independent
Requires-Python: >=3.6
License-File: LICENSE
Requires-Dist: pyserial
Requires-Dist: pylsl
Requires-Dist: pydbus
Requires-Dist: numpy
Requires-Dist: matplotlib
